calcing.py
calcing-1.0.0.dist-info/METADATA
calcing-1.0.0.dist-info/WHEEL
calcing-1.0.0.dist-info/RECORD
