Metadata-Version: 2.3
Name: calcing
Version: 1.0.0
Summary: calcing.plus() calcing.minus() calcing.mnoz() calcing.dil() calcing.diln()
Author: kasked
Requires-Python: >=3.12
Classifier: Programming Language :: Python :: 3
Classifier: Programming Language :: Python :: 3.12
Classifier: Programming Language :: Python :: 3.13
